Workbook

Sheet Instrucciones
B2: Carga masiva a Mercado Libre — productos nuevos de la PI10196
B3: Importación IMP1780969938902 · orden 21/05/2026 · recibida 12/09/2026 · 33 ítems, 22 de ellos sin publicación previa.
B5: Qué contiene este archivo
B6: • Publicaciones — una fila por SKU nuevo, con todos los campos que pide el cargador masivo de Mercado Libre. Es la hoja que copiás a la plantilla de ML.
B7: • Costos PI10196 — el costo real de cada SKU con el prorrateo de la importación aplicado, y el precio sugerido que alimenta la columna Precio de la hoja Publicaciones.
B8: • Parametros — los tres supuestos que mueven todos los números. Editalos ahí y el resto se recalcula solo.
B10: Antes de subir: dos cosas bloquean la carga
B11: 1. FOTOS. Mercado Libre rechaza cualquier publicación sin al menos una imagen. La columna Fotos está vacía y marcada en amarillo. Hay que completarla antes de subir.
B12: 2. PRECIO. Los 22 SKUs no tenían precio de venta definido. La columna Precio trae un valor calculado a partir del costo real × un markup de referencia tomado de productos similares de tu propio catálogo. Es un placeholder para que la fila sea válida, no un precio decidido. Por eso todas las filas van con Estado inicial = pausado.
B14: Cómo se usa
B15: 1. Completá la columna Fotos (una o más URLs separadas por coma) y revisá Precio.
B16: 2. En Mercado Libre: Mis publicaciones → Publicar → Carga masiva. El cargador pide elegir la categoría primero y recién ahí te da la plantilla .xlsx de esa categoría.
... B30: Negro = calculado por fórmula.

Sheet Parametros
B2: Parámetros de la PI10196
B4: Concepto | C4: Valor | D4: De dónde sale
B5: Total pagado por la importación (USD) | C5: 1467 | D5: Campo total del registro IMP1780969938902 en Supabase. Incluye mercadería, traslado interno (USD 12,80), nacionalización (USD 810) e IVA.
B6: Costo declarado de los 33 ítems (USD) | C6: 685.2 | D6: Suma de qty × costo de los 33 ítems de la importación. Son los 33, no sólo los 22 nuevos: el prorrateo reparte los gastos sobre toda la carga.
B7: Factor de prorrateo | C7: =C5/C6 -> 2.1409807 | D7: Cuánto multiplica el costo declarado para llegar al costo real puesto en depósito. Misma fórmula que usa la pantalla de Importaciones.
B8: Tipo de cambio UYU/USD | C8: 42 | D8: SUPUESTO. Es el TC implícito en los SKUs de esta misma PI que ya están cargados: ALERONFINOSNK, HSJ-20121, HS-30006 y los DOM tienen costo = declarado × 90, y 90 / 2,1410 = 42. Cambialo acá si usaste otro.
B9: Precio mínimo de publicación (UYU) | C9: 290 | D9: SUPUESTO MÍO, revisalo. Piso para que los extensores no queden a $216. Ningún precio sugerido baja de este valor.
B11: Los dos valores en amarillo son supuestos míos, no datos de la importación. Todo lo demás sale del registro de la PI10196.

Sheet Costos PI10196
A1: Costo real por SKU — productos nuevos de la PI10196
A2: Costo real = costo declarado × factor de prorrateo × tipo de cambio. El markup es editable: cambialo y el precio sugerido se recalcula.
A4: SKU | B4: Producto | C4: Categoría destino | D4: Cantidad recibida | E4: Costo declarado USD | F4: Costo declarado total USD | G4: Costo real USD | H4: Costo real UYU | I4: Markup | J4: Precio calculado | K4: Precio sugerido | L4: Comparable en tu catálogo
A5: SOP-CEL-MAN-001 | B5: Soporte Celular Moto Universal Manillar Negro Ajustable | C5: Soportes de Celular | D5: 100 | E5: 1 | F5: =D5*E5 -> 100 | G5: =E5*Parametros!$C$7 -> 2.1409807 | H5: =G5*Parametros!$C$8 -> 89.921191 | I5: 8 | J5: =ROUND(H5*I5,0) -> 719 | K5: =MAX(J5,Parametros!$C$9) -> 719 | L5: sin comparable
A6: SOP-CEL-ESP-001 | B6: Soporte Celular Moto Universal Espejo Negro Ajustable | C6: Soportes de Celular | D6: 100 | E6: 1 | F6: =D6*E6 -> 100 | G6: =E6*Parametros!$C$7 -> 2.1409807 | H6: =G6*Parametros!$C$8 -> 89.921191 | I6: 8 | J6: =ROUND(H6*I6,0) -> 719 | K6: =MAX(J6,Parametros!$C$9) -> 719 | L6: sin comparable
A7: ESP-CIR-001 | B7: Espejos de Puño Circulares Moto Universal Manillar 7/8 Negro | C7: Espejos | D7: 10 | E7: 3.8 | F7: =D7*E7 -> 38 | G7: =E7*Parametros!$C$7 -> 8.1357268 | H7: =G7*Parametros!$C$8 -> 341.70053 | I7: 3.1 | J7: =ROUND(H7*I7,0) -> 1059 | K7: =MAX(J7,Parametros!$C$9) -> 1059 | L7: HP-SH-5003-L — $ 1.290
A8: MAN-78-V2-NEG-001 | B8: Manillar Moto Universal 7/8 22mm Alto Negro Antideslizante | C8: Manubrios y Manillares | D8: 5 | E8: 2.7 | F8: =D8*E8 -> 13.5 | G8: =E8*Parametros!$C$7 -> 5.780648 | H8: =G8*Parametros!$C$8 -> 242.78722 | I8: 2.46 | J8: =ROUND(H8*I8,0) -> 597 | K8: =MAX(J8,Parametros!$C$9) -> 597 | L8: HP-CB0381 — $ 1.190
A9: MAN-78-V2-PLA-001 | B9: Manillar Moto Universal 7/8 22mm Alto Plateado Antideslizante | C9: Manubrios y Manillares | D9: 5 | E9: 2.7 | F9: =D9*E9 -> 13.5 | G9: =E9*Parametros!$C$7 -> 5.780648 | H9: =G9*Parametros!$C$8 -> 242.78722 | I9: 2.46 | J9: =ROUND(H9*I9,0) -> 597 | K9: =MAX(J9,Parametros!$C$9) -> 597 | L9: HP-CB0381 — $ 1.190
A10: MAN-78-V3-PLA-001 | B10: Manillar Café Racer Universal 7/8 22mm Recto Plateado Cromado | C10: Manubrios y Manillares | D10: 5 | E10: 3 | F10: =D10*E10 -> 15 | G10: =E10*Parametros!$C$7 -> 6.4229422 | H10: =G10*Parametros!$C$8 -> 269.76357 | I10: 2.46 | J10: =ROUND(H10*I10,0) -> 664 | K10: =MAX(J10,Parametros!$C$9) -> 664 | L10: HP-CB0381 — $ 1.190
A11: EXT-ESP-8F-8F-001 | B11: Extensor Espejo Moto Rosca 8mm Int/Ext Horario Universal | C11: Extensores de Espejo | D11: 10 | E11: 0.12 | F11: =D11*E11 -> 1.2 | G11: =E11*Parametros!$C$7 -> 0.25691769 | H11: =G11*Parametros!$C$8 -> 10.790543 | I11: 20 | J11: =ROUND(H11*I11,0) -> 216 | K11: =MAX(J11,Parametros!$C$9) -> 290 | L11: sin comparable
A12: EXT-ESP-8F-8R-001 | B12: Extensor Espejo Moto Rosca 8mm Int Hor / Ext Antihor | C12: Extensores de Espejo | D12: 10 | E12: 0.12 | F12: =D12*E12 -> 1.2 | G12: =E12*Parametros!$C$7 -> 0.25691769 | H12: =G12*Parametros!$C$8 -> 10.790543 | I12: 20 | J12: =ROUND(H12*I12,0) -> 216 | K12: =MAX(J12,Parametros!$C$9) -> 290 | L12: sin comparable
A13: EXT-ESP-8R-8F-001 | B13: Extensor Espejo Moto Rosca 8mm Int Antihor / Ext Hor | C13: Extensores de Espejo | D13: 10 | E13: 0.12 | F13: =D13*E13 -> 1.2 | G13: =E13*Parametros!$C$7 -> 0.25691769 | H13: =G13*Parametros!$C$8 -> 10.790543 | I13: 20 | J13: =ROUND(H13*I13,0) -> 216 | K13: =MAX(J13,Parametros!$C$9) -> 290 | L13: sin comparable
A14: EXT-ESP-8R-8R-001 | B14: Extensor Espejo Moto Rosca 8mm Int/Ext Antihorario Univ | C14: Extensores de Espejo | D14: 10 | E14: 0.12 | F14: =D14*E14 -> 1.2 | G14: =E14*Parametros!$C$7 -> 0.25691769 | H14: =G14*Parametros!$C$8 -> 10.790543 | I14: 20 | J14: =ROUND(H14*I14,0) -> 216 | K14: =MAX(J14,Parametros!$C$9) -> 290 | L14: sin comparable
A15: EXT-ESP-8F-10F-001 | B15: Extensor Espejo Moto Rosca 8mm Int Hor / 10mm Ext Hor | C15: Extensores de Espejo | D15: 10 | E15: 0.12 | F15: =D15*E15 -> 1.2 | G15: =E15*Parametros!$C$7 -> 0.25691769 | H15: =G15*Parametros!$C$8 -> 10.790543 | I15: 20 | J15: =ROUND(H15*I15,0) -> 216 | K15: =MAX(J15,Parametros!$C$9) -> 290 | L15: sin comparable
A16: EXT-ESP-8R-10F-001 | B16: Extensor Espejo Moto Rosca 8mm Int Antihor / 10mm Ext | C16: Extensores de Espejo | D16: 10 | E16: 0.12 | F16: =D16*E16 -> 1.2 | G16: =E16*Parametros!$C$7 -> 0.25691769 | H16: =G16*Parametros!$C$8 -> 10.790543 | I16: 20 | J16: =ROUND(H16*I16,0) -> 216 | K16: =MAX(J16,Parametros!$C$9) -> 290 | L16: sin comparable
... A26: EXT-ESP-10R-8R-001 | B26: Extensor Espejo Moto Rosca 10mm Int/8mm Ext Antihorario | C26: Extensores de Espejo | D26: 10 | E26: 0.12 | F26: =D26*E26 -> 1.2 | G26: =E26*Parametros!$C$7 -> 0.25691769 | H26: =G26*Parametros!$C$8 -> 10.790543 | I26: 20 | J26: =ROUND(H26*I26,0) -> 216 | K26: =MAX(J26,Parametros!$C$9) -> 290 | L26: sin comparable
C27: TOTAL 22 SKUs nuevos | D27: =SUM(D5:D26) -> 385 | F27: =SUM(F5:F26) -> 299.2
A29: Markups de referencia tomados de tu catálogo: espejos de puño 3,10x (HP-SH-5003-L), manillares 2,46x (HP-CB0381..85), accesorios de bajo costo 8x–20x (PATENTE1 8,24x, HP-MG072 7,98x, FSB-002 7,17x). Los soportes de celular y los extensores no tienen comparable directo: ahí el markup es estimado.
A30: Los 11 SKUs restantes de la PI10196 (ALERONFINOSNK, CPJ-62001, DOM00..03, HP-CB0381, HS-30006, HSJ-20121, PUNBLACK, PUNRED) ya están publicados y no entran en esta planilla.

Sheet Publicaciones
A1: Publicaciones a crear — 22 SKUs nuevos de la PI10196
A2: Completá Fotos (obligatorio para ML) y revisá Precio. Después copiá cada grupo a la plantilla de carga masiva de su categoría.
A3: Columnas en amarillo = las completás vos. La fila 5 es un EJEMPLO del formato esperado, borrala antes de subir. Precio viene de la hoja Costos PI10196.
A4: Categoría destino | B4: Categoría sugerida en ML | C4: Título | D4: Largo título | E4: SKU | F4: Precio | G4: Moneda | H4: Stock disponible | I4: Condición | J4: Tipo de publicación | K4: Estado inicial | L4: Fotos (URLs separadas por coma) | M4: Marca | N4: Modelo | O4: Garantía | P4: Descripción
A5: EJEMPLO — borrar | B5: Accesorios para Vehículos > ... > Espejos | C5: Espejo Redondo Moto Universal Rosca 10mm Negro | D5: =LEN(C5) -> 46 | E5: EJEMPLO-001 | F5: 1290 | G5: UYU | H5: 12 | I5: Nuevo | J5: Clásica | K5: pausado | L5: https://midominio.com/fotos/ej-1.jpg, https://midominio.com/fotos/ej-2.jpg | M5: Genérica | N5: Universal | O5: Sin garantía | P5: Espejo universal para moto. - Rosca 10mm. - Cuerpo de aluminio.
A6: Soportes de Celular | B6: Accesorios para Vehículos > Acc. para Motos y Cuatriciclos > Soportes y Bases | C6: Soporte Celular Moto Universal Espejo Negro Ajustable | D6: =LEN(C6) -> 53 | E6: SOP-CEL-ESP-001 | F6: ='Costos PI10196'!K6 -> 719 | G6: UYU | H6: 100 | I6: Nuevo | J6: Clásica | K6: pausado | M6: Genérica | N6: Universal | O6: Sin garantía | P6: Soporte universal para celular apto para moto, con anclaje a la base del espejo. - Sujeción ajustable: se adapta a celulares de 4,7" a 7". - Rotación 360°: podés usarlo en vertical u horizontal. - Construcción en ABS reforzado con gomas antivibración. - Instalación sin herramientas especiales. Producto nuevo. Envíos a todo el país.
A7: Soportes de Celular | B7: Accesorios para Vehículos > Acc. para Motos y Cuatriciclos > Soportes y Bases | C7: Soporte Celular Moto Universal Manillar Negro Ajustable | D7: =LEN(C7) -> 55 | E7: SOP-CEL-MAN-001 | F7: ='Costos PI10196'!K5 -> 719 | G7: UYU | H7: 100 | I7: Nuevo | J7: Clásica | K7: pausado | M7: Genérica | N7: Universal | O7: Sin garantía | P7: Soporte universal para celular apto para moto, con anclaje al manillar. - Sujeción ajustable: se adapta a celulares de 4,7" a 7". - Rotación 360°: podés usarlo en vertical u horizontal. - Construcción en ABS reforzado con gomas antivibración. - Instalación sin herramientas especiales. Producto nuevo. Envíos a todo el país.
A8: Espejos | B8: Accesorios para Vehículos > Acc. para Motos y Cuatriciclos > Espejos | C8: Espejos de Puño Circulares Moto Universal Manillar 7/8 Negro | D8: =LEN(C8) -> 60 | E8: ESP-CIR-001 | F8: ='Costos PI10196'!K7 -> 1059 | G8: UYU | H8: 10 | I8: Nuevo | J8: Clásica | K8: pausado | M8: Genérica | N8: Universal | O8: Sin garantía | P8: Par de espejos de puño circulares para moto, universales. - Montaje en manillar de 7/8" (22mm). - Cuerpo de aluminio con terminación negra. - Brazo y cabezal regulables para ajustar el ángulo de visión. - Se venden por par (izquierdo y derecho). Producto nuevo. Envíos a todo el país.
A9: Extensores de Espejo | B9: Accesorios para Vehículos > Acc. para Motos y Cuatriciclos > Espejos | C9: Extensor Espejo Moto Rosca 10mm Int/Ext Horario Universal | D9: =LEN(C9) -> 57 | E9: EXT-ESP-10F-10F-001 | F9: ='Costos PI10196'!K19 -> 290 | G9: UYU | H9: 10 | I9: Nuevo | J9: Clásica | K9: pausado | M9: Genérica | N9: Universal | O9: Sin garantía | P9: Extensor / adaptador de rosca para espejo de moto. - Rosca interior: 10mm horario. - Rosca exterior: 10mm horario. - Permite montar espejos con rosca distinta a la del soporte original y ganar altura para mejorar el campo de visión. - Acero con terminación negra. - Se vende por unidad. Producto nuevo. Envíos a todo el país.
A10: Extensores de Espejo | B10: Accesorios para Vehículos > Acc. para Motos y Cuatriciclos > Espejos | C10: Extensor Espejo Moto Rosca 10mm Int Hor / Ext Antihor | D10: =LEN(C10) -> 53 | E10: EXT-ESP-10F-10R-001 | F10: ='Costos PI10196'!K21 -> 290 | G10: UYU | H10: 10 | I10: Nuevo | J10: Clásica | K10: pausado | M10: Genérica | N10: Universal | O10: Sin garantía | P10: Extensor / adaptador de rosca para espejo de moto. - Rosca interior: 10mm horario. - Rosca exterior: 10mm antihorario. - Permite montar espejos con rosca distinta a la del soporte original y ganar altura para mejorar el campo de visión. - Acero con terminación negra. - Se vende por unidad. Producto nuevo. Envíos a todo el país.
A11: Extensores de Espejo | B11: Accesorios para Vehículos > Acc. para Motos y Cuatriciclos > Espejos | C11: Extensor Espejo Moto Rosca 10mm Int Hor / 8mm Ext Hor | D11: =LEN(C11) -> 53 | E11: EXT-ESP-10F-8F-001 | F11: ='Costos PI10196'!K23 -> 290 | G11: UYU | H11: 10 | I11: Nuevo | J11: Clásica | K11: pausado | M11: Genérica | N11: Universal | O11: Sin garantía | P11: Extensor / adaptador de rosca para espejo de moto. - Rosca interior: 10mm horario. - Rosca exterior: 8mm horario. - Permite montar espejos con rosca distinta a la del soporte original y ganar altura para mejorar el campo de visión. - Acero con terminación negra. - Se vende por unidad. Producto nuevo. Envíos a todo el país.
A12: Extensores de Espejo | B12: Accesorios para Vehículos > Acc. para Motos y Cuatriciclos > Espejos | C12: Extensor Espejo Moto Rosca 10mm Int Hor / 8mm Ext Antihor | D12: =LEN(C12) -> 57 | E12: EXT-ESP-10F-8R-001 | F12: ='Costos PI10196'!K24 -> 290 | G12: UYU | H12: 10 | I12: Nuevo | J12: Clásica | K12: pausado | M12: Genérica | N12: Universal | O12: Sin garantía | P12: Extensor / adaptador de rosca para espejo de moto. - Rosca interior: 10mm horario. - Rosca exterior: 8mm antihorario. - Permite montar espejos con rosca distinta a la del soporte original y ganar altura para mejorar el campo de visión. - Acero con terminación negra. - Se vende por unidad. Producto nuevo. Envíos a todo el país.
A13: Extensores de Espejo | B13: Accesorios para Vehículos > Acc. para Motos y Cuatriciclos > Espejos | C13: Extensor Espejo Moto Rosca 10mm Int Antihor / Ext Hor | D13: =LEN(C13) -> 53 | E13: EXT-ESP-10R-10F-001 | F13: ='Costos PI10196'!K20 -> 290 | G13: UYU | H13: 10 | I13: Nuevo | J13: Clásica | K13: pausado | M13: Genérica | N13: Universal | O13: Sin garantía | P13: Extensor / adaptador de rosca para espejo de moto. - Rosca interior: 10mm antihorario. - Rosca exterior: 10mm horario. - Permite montar espejos con rosca distinta a la del soporte original y ganar altura para mejorar el campo de visión. - Acero con terminación negra. - Se vende por unidad. Producto nuevo. Envíos a todo el país.
A14: Extensores de Espejo | B14: Accesorios para Vehículos > Acc. para Motos y Cuatriciclos > Espejos | C14: Extensor Espejo Moto Rosca 10mm Int/Ext Antihorario Univ | D14: =LEN(C14) -> 56 | E14: EXT-ESP-10R-10R-001 | F14: ='Costos PI10196'!K22 -> 290 | G14: UYU | H14: 10 | I14: Nuevo | J14: Clásica | K14: pausado | M14: Genérica | N14: Universal | O14: Sin garantía | P14: Extensor / adaptador de rosca para espejo de moto. - Rosca interior: 10mm antihorario. - Rosca exterior: 10mm antihorario. - Permite montar espejos con rosca distinta a la del soporte original y ganar altura para mejorar el campo de visión. - Acero con terminación negra. - Se vende por unidad. Producto nuevo. Envíos a todo el país.
A15: Extensores de Espejo | B15: Accesorios para Vehículos > Acc. para Motos y Cuatriciclos > Espejos | C15: Extensor Espejo Moto Rosca 10mm Int Antihor / 8mm Ext | D15: =LEN(C15) -> 53 | E15: EXT-ESP-10R-8F-001 | F15: ='Costos PI10196'!K25 -> 290 | G15: UYU | H15: 10 | I15: Nuevo | J15: Clásica | K15: pausado | M15: Genérica | N15: Universal | O15: Sin garantía | P15: Extensor / adaptador de rosca para espejo de moto. - Rosca interior: 10mm antihorario. - Rosca exterior: 8mm horario. - Permite montar espejos con rosca distinta a la del soporte original y ganar altura para mejorar el campo de visión. - Acero con terminación negra. - Se vende por unidad. Producto nuevo. Envíos a todo el país.
A16: Extensores de Espejo | B16: Accesorios para Vehículos > Acc. para Motos y Cuatriciclos > Espejos | C16: Extensor Espejo Moto Rosca 10mm Int/8mm Ext Antihorario | D16: =LEN(C16) -> 55 | E16: EXT-ESP-10R-8R-001 | F16: ='Costos PI10196'!K26 -> 290 | G16: UYU | H16: 10 | I16: Nuevo | J16: Clásica | K16: pausado | M16: Genérica | N16: Universal | O16: Sin garantía | P16: Extensor / adaptador de rosca para espejo de moto. - Rosca interior: 10mm antihorario. - Rosca exterior: 8mm antihorario. - Permite montar espejos con rosca distinta a la del soporte original y ganar altura para mejorar el campo de visión. - Acero con terminación negra. - Se vende por unidad. Producto nuevo. Envíos a todo el país.
A17: Extensores de Espejo | B17: Accesorios para Vehículos > Acc. para Motos y Cuatriciclos > Espejos | C17: Extensor Espejo Moto Rosca 8mm Int Hor / 10mm Ext Hor | D17: =LEN(C17) -> 53 | E17: EXT-ESP-8F-10F-001 | F17: ='Costos PI10196'!K15 -> 290 | G17: UYU | H17: 10 | I17: Nuevo | J17: Clásica | K17: pausado | M17: Genérica | N17: Universal | O17: Sin garantía | P17: Extensor / adaptador de rosca para espejo de moto. - Rosca interior: 8mm horario. - Rosca exterior: 10mm horario. - Permite montar espejos con rosca distinta a la del soporte original y ganar altura para mejorar el campo de visión. - Acero con terminación negra. - Se vende por unidad. Producto nuevo. Envíos a todo el país.
A18: Extensores de Espejo | B18: Accesorios para Vehículos > Acc. para Motos y Cuatriciclos > Espejos | C18: Extensor Espejo Moto Rosca 8mm Int Hor / 10mm Ext Antihor | D18: =LEN(C18) -> 57 | E18: EXT-ESP-8F-10R-001 | F18: ='Costos PI10196'!K17 -> 290 | G18: UYU | H18: 10 | I18: Nuevo | J18: Clásica | K18: pausado | M18: Genérica | N18: Universal | O18: Sin garantía | P18: Extensor / adaptador de rosca para espejo de moto. - Rosca interior: 8mm horario. - Rosca exterior: 10mm antihorario. - Permite montar espejos con rosca distinta a la del soporte original y ganar altura para mejorar el campo de visión. - Acero con terminación negra. - Se vende por unidad. Producto nuevo. Envíos a todo el país.
A19: Extensores de Espejo | B19: Accesorios para Vehículos > Acc. para Motos y Cuatriciclos > Espejos | C19: Extensor Espejo Moto Rosca 8mm Int/Ext Horario Universal | D19: =LEN(C19) -> 56 | E19: EXT-ESP-8F-8F-001 | F19: ='Costos PI10196'!K11 -> 290 | G19: UYU | H19: 10 | I19: Nuevo | J19: Clásica | K19: pausado | M19: Genérica | N19: Universal | O19: Sin garantía | P19: Extensor / adaptador de rosca para espejo de moto. - Rosca interior: 8mm horario. - Rosca exterior: 8mm horario. - Permite montar espejos con rosca distinta a la del soporte original y ganar altura para mejorar el campo de visión. - Acero con terminación negra. - Se vende por unidad. Producto nuevo. Envíos a todo el país.
A20: Extensores de Espejo | B20: Accesorios para Vehículos > Acc. para Motos y Cuatriciclos > Espejos | C20: Extensor Espejo Moto Rosca 8mm Int Hor / Ext Antihor | D20: =LEN(C20) -> 52 | E20: EXT-ESP-8F-8R-001 | F20: ='Costos PI10196'!K12 -> 290 | G20: UYU | H20: 10 | I20: Nuevo | J20: Clásica | K20: pausado | M20: Genérica | N20: Universal | O20: Sin garantía | P20: Extensor / adaptador de rosca para espejo de moto. - Rosca interior: 8mm horario. - Rosca exterior: 8mm antihorario. - Permite montar espejos con rosca distinta a la del soporte original y ganar altura para mejorar el campo de visión. - Acero con terminación negra. - Se vende por unidad. Producto nuevo. Envíos a todo el país.
A21: Extensores de Espejo | B21: Accesorios para Vehículos > Acc. para Motos y Cuatriciclos > Espejos | C21: Extensor Espejo Moto Rosca 8mm Int Antihor / 10mm Ext | D21: =LEN(C21) -> 53 | E21: EXT-ESP-8R-10F-001 | F21: ='Costos PI10196'!K16 -> 290 | G21: UYU | H21: 10 | I21: Nuevo | J21: Clásica | K21: pausado | M21: Genérica | N21: Universal | O21: Sin garantía | P21: Extensor / adaptador de rosca para espejo de moto. - Rosca interior: 8mm antihorario. - Rosca exterior: 10mm horario. - Permite montar espejos con rosca distinta a la del soporte original y ganar altura para mejorar el campo de visión. - Acero con terminación negra. - Se vende por unidad. Producto nuevo. Envíos a todo el país.
A22: Extensores de Espejo | B22: Accesorios para Vehículos > Acc. para Motos y Cuatriciclos > Espejos | C22: Extensor Espejo Moto Rosca 8mm Int/10mm Ext Antihorario | D22: =LEN(C22) -> 55 | E22: EXT-ESP-8R-10R-001 | F22: ='Costos PI10196'!K18 -> 290 | G22: UYU | H22: 10 | I22: Nuevo | J22: Clásica | K22: pausado | M22: Genérica | N22: Universal | O22: Sin garantía | P22: Extensor / adaptador de rosca para espejo de moto. - Rosca interior: 8mm antihorario. - Rosca exterior: 10mm antihorario. - Permite montar espejos con rosca distinta a la del soporte original y ganar altura para mejorar el campo de visión. - Acero con terminación negra. - Se vende por unidad. Producto nuevo. Envíos a todo el país.
A23: Extensores de Espejo | B23: Accesorios para Vehículos > Acc. para Motos y Cuatriciclos > Espejos | C23: Extensor Espejo Moto Rosca 8mm Int Antihor / Ext Hor | D23: =LEN(C23) -> 52 | E23: EXT-ESP-8R-8F-001 | F23: ='Costos PI10196'!K13 -> 290 | G23: UYU | H23: 10 | I23: Nuevo | J23: Clásica | K23: pausado | M23: Genérica | N23: Universal | O23: Sin garantía | P23: Extensor / adaptador de rosca para espejo de moto. - Rosca interior: 8mm antihorario. - Rosca exterior: 8mm horario. - Permite montar espejos con rosca distinta a la del soporte original y ganar altura para mejorar el campo de visión. - Acero con terminación negra. - Se vende por unidad. Producto nuevo. Envíos a todo el país.
A24: Extensores de Espejo | B24: Accesorios para Vehículos > Acc. para Motos y Cuatriciclos > Espejos | C24: Extensor Espejo Moto Rosca 8mm Int/Ext Antihorario Univ | D24: =LEN(C24) -> 55 | E24: EXT-ESP-8R-8R-001 | F24: ='Costos PI10196'!K14 -> 290 | G24: UYU | H24: 10 | I24: Nuevo | J24: Clásica | K24: pausado | M24: Genérica | N24: Universal | O24: Sin garantía | P24: Extensor / adaptador de rosca para espejo de moto. - Rosca interior: 8mm antihorario. - Rosca exterior: 8mm antihorario. - Permite montar espejos con rosca distinta a la del soporte original y ganar altura para mejorar el campo de visión. - Acero con terminación negra. - Se vende por unidad. Producto nuevo. Envíos a todo el país.
A25: Manubrios y Manillares | B25: Accesorios para Vehículos > Acc. para Motos y Cuatriciclos > Manubrios | C25: Manillar Moto Universal 7/8 22mm Alto Negro Antideslizante | D25: =LEN(C25) -> 58 | E25: MAN-78-V2-NEG-001 | F25: ='Costos PI10196'!K8 -> 597 | G25: UYU | H25: 5 | I25: Nuevo | J25: Clásica | K25: pausado | M25: Genérica | N25: Universal | O25: Sin garantía | P25: Manillar alto con superficie antideslizante, universal para moto, en negro. - Medida universal 7/8" (22mm) de diámetro. - Aluminio de alta resistencia. - Compatible con puños, espejos y comandos estándar. - Se vende por unidad. Producto nuevo. Envíos a todo el país.
A26: Manubrios y Manillares | B26: Accesorios para Vehículos > Acc. para Motos y Cuatriciclos > Manubrios | C26: Manillar Moto Universal 7/8 22mm Alto Plateado | D26: =LEN(C26) -> 46 | E26: MAN-78-V2-PLA-001 | F26: ='Costos PI10196'!K9 -> 597 | G26: UYU | H26: 5 | I26: Nuevo | J26: Clásica | K26: pausado | M26: Genérica | N26: Universal | O26: Sin garantía | P26: Manillar alto con superficie antideslizante, universal para moto, en plateado cromado. - Medida universal 7/8" (22mm) de diámetro. - Aluminio de alta resistencia. - Compatible con puños, espejos y comandos estándar. - Se vende por unidad. Producto nuevo. Envíos a todo el país.
A27: Manubrios y Manillares | B27: Accesorios para Vehículos > Acc. para Motos y Cuatriciclos > Manubrios | C27: Manillar Café Racer Universal 7/8 22mm Recto Cromado | D27: =LEN(C27) -> 52 | E27: MAN-78-V3-PLA-001 | F27: ='Costos PI10196'!K10 -> 664 | G27: UYU | H27: 5 | I27: Nuevo | J27: Clásica | K27: pausado | M27: Genérica | N27: Universal | O27: Sin garantía | P27: Manillar tipo Café Racer, recto, universal para moto, en plateado cromado. - Medida universal 7/8" (22mm) de diámetro. - Aluminio de alta resistencia. - Compatible con puños, espejos y comandos estándar. - Se vende por unidad. Producto nuevo. Envíos a todo el país.
A29: Largo título: Mercado Libre corta en 60 caracteres. Los que se pasan hay que acortarlos antes de subir.
A30: Marca / Modelo / Garantía: valores por defecto. Si la plantilla de la categoría pide atributos adicionales (material, color, tipo de rosca), completalos ahí.
A31: Tipo de publicación: 'Clásica' es el default. Si querés Premium, cambialo antes de subir — cambia la comisión.
